__muffle__/__init__.py
__muffle__/app.py
__muffle__/conf.yml
__muffle__/fuzzy.py
__muffle__/log.py
__muffle__/muffle.py
__muffle__/requirements.txt
fuzzy_muffler-0.0.4.dist-info/METADATA
fuzzy_muffler-0.0.4.dist-info/WHEEL
fuzzy_muffler-0.0.4.dist-info/entry_points.txt
fuzzy_muffler-0.0.4.dist-info/top_level.txt
fuzzy_muffler-0.0.4.dist-info/RECORD
