Metadata-Version: 2.1
Name: fuzzy-muffler
Version: 0.0.4
Summary: mp3|ogg|wav audio muffler/fuzifier
Home-page: https://github.com/hashirkz/muffle_audio
Author: hashirkz
Author-email: hashir.khan@mail.mcgill.ca
Classifier: Programming Language :: Python :: 3
Classifier: Operating System :: POSIX
Requires-Dist: numpy (==1.23.0)
Requires-Dist: matplotlib (==3.3.0)
Requires-Dist: pandas (==2.0.2)
Requires-Dist: scipy (==1.5.2)
Requires-Dist: librosa (==0.10.1)
Requires-Dist: pyrubberband (==0.3.0)
Requires-Dist: pyyaml (==5.4.1)
